README.md
setup.cfg
setup.py
src/animal_avatar/__init__.py
src/animal_avatar/animal_avatar.py
src/animal_avatar.egg-info/PKG-INFO
src/animal_avatar.egg-info/SOURCES.txt
src/animal_avatar.egg-info/dependency_links.txt
src/animal_avatar.egg-info/top_level.txt
src/animal_avatar/palette/__init__.py
src/animal_avatar/palette/consts.py
src/animal_avatar/shapes/__init__.py
src/animal_avatar/shapes/brows.py
src/animal_avatar/shapes/ears.py
src/animal_avatar/shapes/eyes.py
src/animal_avatar/shapes/faces.py
src/animal_avatar/shapes/hairs.py
src/animal_avatar/shapes/muzzles.py
src/animal_avatar/shapes/patterns.py
src/animal_avatar/utils/__init__.py
src/animal_avatar/utils/array.py
src/animal_avatar/utils/colors.py
src/animal_avatar/utils/rand.py
src/animal_avatar/utils/svg.py
test/test_rand.py
test/test_svg.py