Metadata-Version: 1.2
Name: animal-avatar
Version: 0.0.5
Summary: SVG avatar generator.
Home-page: https://github.com/Nacht1gall/animal-avatar-generator
Author-email: johnherbertdillinger@ukr.net
License: MIT
Download-URL: https://github.com/Nacht1gall/animal-avatar-generator/archive/refs/heads/master.zip
Keywords: AVATAR,SVG
Platform: any
Classifier: Development Status :: 3 - Alpha
Classifier: Operating System :: OS Independent
Classifier: Intended Audience :: Developers
Classifier: Topic :: Software Development :: Build Tools
Classifier: License :: OSI Approved :: MIT License
Classifier: Programming Language :: Python :: 3
Classifier: Programming Language :: Python :: 3.7
Classifier: Programming Language :: Python :: 3.8
Classifier: Programming Language :: Python :: 3.9
Classifier: Programming Language :: Python :: 3.10
Requires-Python: >=3.7
